veracode_api_signing/__init__.py
veracode_api_signing/_version.py
veracode_api_signing/cli.py
veracode_api_signing/credentials.py
veracode_api_signing/exceptions.py
veracode_api_signing/formatters.py
veracode_api_signing/plugin_httpie.py
veracode_api_signing/plugin_requests.py
veracode_api_signing/regions.py
veracode_api_signing/utils.py
veracode_api_signing/validation.py
veracode_api_signing/veracode_hmac_auth.py
veracode_api_signing-26.1.0.dist-info/licenses/LICENSE
veracode_api_signing-26.1.0.dist-info/METADATA
veracode_api_signing-26.1.0.dist-info/WHEEL
veracode_api_signing-26.1.0.dist-info/entry_points.txt
veracode_api_signing-26.1.0.dist-info/top_level.txt
veracode_api_signing-26.1.0.dist-info/RECORD
