Metadata-Version: 2.4
Name: veracode-api-signing
Version: 26.1.0
Summary: Easily sign any request destined for the Veracode API Gateway
Home-page: https://docs.veracode.com/r/t_install_api_authen
Author: Veracode
License: MIT
Keywords: veracode-api-signing
Classifier: License :: OSI Approved :: MIT License
Classifier: Development Status :: 5 - Production/Stable
Classifier: Environment :: Plugins
Classifier: Intended Audience :: Developers
Classifier: Natural Language :: English
Classifier: Programming Language :: Python :: 3
Classifier: Programming Language :: Python :: 3.9
Classifier: Programming Language :: Python :: 3.10
Classifier: Programming Language :: Python :: 3.11
Classifier: Programming Language :: Python :: 3.12
Classifier: Programming Language :: Python :: 3.13
Classifier: Topic :: Security
Classifier: Topic :: Software Development :: Libraries :: Python Modules
Classifier: Topic :: Internet :: WWW/HTTP
Classifier: Topic :: Utilities
Requires-Python: >=3.9
License-File: LICENSE
Requires-Dist: docopt>=0.6.2
Requires-Dist: httpie>=3.2.4
Requires-Dist: pip>=25.3
Requires-Dist: requests>=2.27.1
Requires-Dist: setuptools>=70.0.0
Dynamic: author
Dynamic: classifier
Dynamic: description
Dynamic: home-page
Dynamic: keywords
Dynamic: license
Dynamic: license-file
Dynamic: requires-dist
Dynamic: requires-python
Dynamic: summary
